{
  "db_name": "PostgreSQL",
  "query": "SELECT id, status, event_id, full_name, email_address FROM ticket WHERE STATUS='ACQUIRED' AND event_id=2",
  "describe": {
    "columns": [
      {
        "ordinal": 0,
        "name": "id",
        "type_info": "Int4"
      },
      {
        "ordinal": 1,
        "name": "status",
        "type_info": "Varchar"
      },
      {
        "ordinal": 2,
        "name": "event_id",
        "type_info": "Int4"
      },
      {
        "ordinal": 3,
        "name": "full_name",
        "type_info": "Varchar"
      },
      {
        "ordinal": 4,
        "name": "email_address",
        "type_info": "Varchar"
      }
    ],
    "parameters": {
      "Left": []
    },
    "nullable": [
      false,
      false,
      false,
      true,
      true
    ]
  },
  "hash": "cdf9891b306e1dd72292c310f209a572a9a480dfca23f4e958773ff4e84e24df"
}
